easymodel-0.5.0.dist-info/DESCRIPTION.rst
easymodel-0.5.0.dist-info/RECORD
easymodel-0.5.0.dist-info/WHEEL
easymodel-0.5.0.dist-info/top_level.txt
easymodel-0.5.0.dist-info/METADATA
easymodel-0.5.0.dist-info/metadata.json
easymodel/widgetdelegate.py
easymodel/treemodel.py
easymodel/__init__.py
easymodel/cascade.py
