Metadata-Version: 2.0
Name: easymodel
Version: 0.5.0
Summary: Qt Models and Views made easy with general purpose Model and a Widget delegate.
Home-page: https://github.com/storax/easymodel
Author: David Zuber
Author-email: zuber.david@gmx.de
License: BSD
Keywords: easymodel
Platform: UNKNOWN
Classifier: Development Status :: 4 - Beta
Classifier: Intended Audience :: Developers
Classifier: License :: OSI Approved :: BSD License
Classifier: Natural Language :: English
Classifier: Programming Language :: Python :: 2.7
Classifier: Programming Language :: Python :: 3.3
Classifier: Programming Language :: Python :: 3.4
Requires-Dist: PySide
